phenoKOR/__init__.py
phenoKOR-0.0.1.dist-info/METADATA
phenoKOR-0.0.1.dist-info/WHEEL
phenoKOR-0.0.1.dist-info/top_level.txt
phenoKOR-0.0.1.dist-info/RECORD
