Metadata-Version: 2.1
Name: phenoKOR
Version: 0.0.1
Summary: phenology package project in KNPS
Home-page: https://github.com/gibum1228/knps_phenology
Author: KNPS_GreenDay
Author-email: gibum1228@gmail.com
Project-URL: issue, https://github.com/gibum1228/knps_phenology/issues
Classifier: Programming Language :: Python :: 3
Classifier: License :: OSI Approved :: MIT License
Requires-Python: >=3.7
